plum_econet/__init__.py
plum_econet/econet.py
plum_econet/exceptions.py
plum_econet/params.py
plum_econet/smartfire.py
plum_econet-0.8.0.dist-info/LICENSE
plum_econet-0.8.0.dist-info/METADATA
plum_econet-0.8.0.dist-info/WHEEL
plum_econet-0.8.0.dist-info/top_level.txt
plum_econet-0.8.0.dist-info/RECORD
