Metadata-Version: 2.1
Name: plum-econet
Version: 0.8.0
Summary: Api wrapper for Plum Econet devices
Author-email: Paweł Tomak <pawel@tomak.eu>
Project-URL: Homepage, https://gitlab.com/bulgur/plum-econet
Project-URL: Bug Tracker, https://gitlab.com/bulgur/plum-econet/-/issues
Classifier: Programming Language :: Python :: 3.10
Classifier: License :: OSI Approved :: MIT License
Classifier: Operating System :: OS Independent
Requires-Python: >=3.7
License-File: LICENSE
Requires-Dist: aiohttp ~=3.8.0
